easy_prime/__init__.py
easy_prime/_sgRNA.py
easy_prime/_target_mutation.py
easy_prime/utils.py
easy_prime-1.2.data/scripts/easy_prime
easy_prime-1.2.data/scripts/easy_prime_vis
model/PE2_model_final.py
model/PE3_model_final.py
model/__init__.py
test/__init__.py
test/rawX_to_bedjs.py
easy_prime-1.2.dist-info/LICENSE
easy_prime-1.2.dist-info/METADATA
easy_prime-1.2.dist-info/WHEEL
easy_prime-1.2.dist-info/top_level.txt
easy_prime-1.2.dist-info/RECORD
