Metadata-Version: 2.1
Name: easy-prime
Version: 1.2
Summary: Prime editor gRNA design tool
Home-page: https://github.com/YichaoOU/easy_prime
Author: Yichao Li
Author-email: Yichao.Li@stjude.org
License: LICENSE
Keywords: prime editor
Platform: UNKNOWN
Classifier: Development Status :: 5 - Production/Stable
Classifier: Intended Audience :: Science/Research
Classifier: Topic :: Scientific/Engineering :: Bio-Informatics
Classifier: Topic :: Scientific/Engineering :: Visualization
Classifier: Topic :: Scientific/Engineering :: Information Analysis
Classifier: Operating System :: Unix
Classifier: Natural Language :: English
Classifier: Programming Language :: Python :: 3
